CHANGES.rst
DESCRIPTION.rst
LICENSE
MANIFEST.in
README.md
setup.py
src/idc/video/__init__.py
src/idc/video/class_lister.py
src/idc/video/filter/__init__.py
src/idc/video/filter/_drop_frames.py
src/idc/video/filter/_filter_frames_by_label.py
src/idc/video/filter/_skip_similar_frames.py
src/idc/video/reader/__init__.py
src/idc/video/reader/_from_video_file.py
src/idc/video/reader/_from_webcam.py
src/idc/video/reader/_youtube.py
src/idc/video/reader/_youtube_live.py
src/idc/video/util/__init__.py
src/idc/video/util/change_detection.py
src/idc/video/writer/__init__.py
src/idc/video/writer/_calc_frame_changes.py
src/idc/video/writer/_to_video_file.py
src/image_dataset_converter_video.egg-info/PKG-INFO
src/image_dataset_converter_video.egg-info/SOURCES.txt
src/image_dataset_converter_video.egg-info/dependency_links.txt
src/image_dataset_converter_video.egg-info/entry_points.txt
src/image_dataset_converter_video.egg-info/requires.txt
src/image_dataset_converter_video.egg-info/top_level.txt